yta_math_common/__init__.py
yta_math_common-0.0.1.dist-info/licenses/LICENSE
yta_math_common-0.0.1.dist-info/METADATA
yta_math_common-0.0.1.dist-info/WHEEL
yta_math_common-0.0.1.dist-info/RECORD
