Metadata-Version: 2.4
Name: yta-math-common
Version: 0.0.1
Summary: Youtube Autonomous Math Common module.
License-File: LICENSE
Author: danialcala94
Author-email: danielalcalavalera@gmail.com
Requires-Python: ==3.9
Classifier: Programming Language :: Python :: 3
Classifier: Programming Language :: Python :: 3.9
Requires-Dist: numpy (>=1.22.0,<3.0.0)
